ComputationalGraphPrimer-1.1.3.html
MANIFEST.in
Makefile
README
setup.py
ComputationalGraphPrimer/ComputationalGraphPrimer.py
ComputationalGraphPrimer/__init__.py
ComputationalGraphPrimer.egg-info/PKG-INFO
ComputationalGraphPrimer.egg-info/SOURCES.txt
ComputationalGraphPrimer.egg-info/dependency_links.txt
ComputationalGraphPrimer.egg-info/top_level.txt
Examples/extending_autograd.py
Examples/graph_based_dataflow.py
Examples/multi_neuron_classifier.py
Examples/one_neuron_classifier.py
Examples/verify_with_torchnn.py
TestComputationalGraphPrimer/ComputationalGraphPrimer.py
TestComputationalGraphPrimer/Test.py
TestComputationalGraphPrimer/TestInstanceCreation.py