Metadata-Version: 1.2
Name: ComputationalGraphPrimer
Version: 1.1.3
Summary: An educational module meant to serve as a prelude to talking about automatic differentiation in deep learning frameworks (for example, as provided by the Autograd module in PyTorch)
Home-page: https://engineering.purdue.edu/kak/distCGP/ComputationalGraphPrimer-1.1.3.html
Author: Avinash Kak
Author-email: kak@purdue.edu
Maintainer: Avinash Kak
Maintainer-email: kak@purdue.edu
License: Python Software Foundation License
Download-URL: https://engineering.purdue.edu/kak/distCGP/ComputationalGraphPrimer-1.1.3.tar.gz
Keywords: computing in a graph
Platform: All platforms
Classifier: Topic :: Scientific/Engineering
Classifier: Programming Language :: Python :: 3.8
